garage61api/__init__.py
garage61api/client.py
garage61api/ids.json
garage61api-0.0.2.dist-info/METADATA
garage61api-0.0.2.dist-info/WHEEL
garage61api-0.0.2.dist-info/licenses/LICENSE
garage61api-0.0.2.dist-info/RECORD
