Metadata-Version: 2.4
Name: garage61api
Version: 0.0.2
Summary: Garage-61-Api is a simple Python wrapper around the Garage61 API.
Project-URL: Homepage, https://github.com/KuzmaLesnoy/garage61api
Project-URL: Issues, https://github.com/KuzmaLesnoy/garage61api/issues
Author-email: Kuzma Lesnoy <kuzmalesnoy@tieler.top>
License-File: LICENSE
Classifier: License :: OSI Approved :: MIT License
Classifier: Operating System :: OS Independent
Classifier: Programming Language :: Python :: 3
Requires-Python: >=3.10
